docsend/__init__.py
docsend/cli.py
docsend/docsend.py
docsend-0.2.0.dist-info/entry_points.txt
docsend-0.2.0.dist-info/WHEEL
docsend-0.2.0.dist-info/METADATA
docsend-0.2.0.dist-info/RECORD
