Metadata-Version: 2.1
Name: docsend
Version: 0.2.0
Summary: convert docsend to pdf or png sequence
License: MIT
Author: banteg
Author-email: banteeg@gmail.com
Requires-Python: >=3.7,<4.0
Classifier: License :: OSI Approved :: MIT License
Classifier: Programming Language :: Python :: 3
Classifier: Programming Language :: Python :: 3.7
Requires-Dist: click (>=7.0,<8.0)
Requires-Dist: pillow (>=5.3,<6.0)
Requires-Dist: requests-html (>=0.9.0,<0.10.0)
